LICENSE
README.txt
setup.py
kimya/__init__.py
kimya.egg-info/PKG-INFO
kimya.egg-info/SOURCES.txt
kimya.egg-info/dependency_links.txt
kimya.egg-info/requires.txt
kimya.egg-info/top_level.txt